agent_observatory/__init__.py
agent_observatory/context.py
agent_observatory/decorators.py
agent_observatory/events.py
agent_observatory/observatory.py
agent_observatory/session.py
agent_observatory/spans.py
agent_observatory/buffering/__init__.py
agent_observatory/buffering/ring_buffer.py
agent_observatory/cli/__init__.py
agent_observatory/cli/main.py
agent_observatory/exporters/__init__.py
agent_observatory/exporters/base.py
agent_observatory/exporters/console.py
agent_observatory/exporters/file.py
agent_observatory/exporters/json.py
agent_observatory/exporters/otel.py
agent_observatory/exporters/worker.py
agent_observatory/internal/__init__.py
agent_observatory/internal/logging.py
agent_observatory/internal/terminal.py
agent_observatory/runtime/__init__.py
agent_observatory/runtime/clock.py
agent_observatory/runtime/errors.py
agent_observatory/runtime/ids.py
agent_observatory-0.1.2.dist-info/METADATA
agent_observatory-0.1.2.dist-info/WHEEL
agent_observatory-0.1.2.dist-info/entry_points.txt
agent_observatory-0.1.2.dist-info/licenses/LICENSE
agent_observatory-0.1.2.dist-info/RECORD
