Metadata-Version: 2.4
Name: agent-observatory
Version: 0.1.2
Summary: Observability primitives for AI agents (tracing and streaming introspection)
Project-URL: Homepage, https://github.com/darshankparmar/agent-observatory
Project-URL: Repository, https://github.com/darshankparmar/agent-observatory
Project-URL: Issues, https://github.com/darshankparmar/agent-observatory/issues
Project-URL: Security, https://github.com/darshankparmar/agent-observatory/security
Author-email: Darshan Parmar <darshanparmar.dev@gmail.com>
License: MIT License
License-File: LICENSE
Keywords: ai-agents,llm,observability,opentelemetry,streaming,tracing
Classifier: License :: OSI Approved :: MIT License
Classifier: Operating System :: OS Independent
Classifier: Programming Language :: Python :: 3
Classifier: Programming Language :: Python :: 3.10
Classifier: Programming Language :: Python :: 3.11
Classifier: Programming Language :: Python :: 3.12
Classifier: Programming Language :: Python :: 3.13
Classifier: Topic :: Software Development :: Libraries :: Python Modules
Requires-Python: >=3.10
Provides-Extra: all
Requires-Dist: livekit-agents>=1.3.10; extra == 'all'
Requires-Dist: livekit-plugins-cartesia>=1.3.10; extra == 'all'
Requires-Dist: livekit-plugins-deepgram>=1.3.10; extra == 'all'
Requires-Dist: livekit-plugins-openai>=1.3.10; extra == 'all'
Requires-Dist: livekit-plugins-silero>=1.3.10; extra == 'all'
Requires-Dist: livekit-plugins-turn-detector>=1.3.10; extra == 'all'
Requires-Dist: mypy; extra == 'all'
Requires-Dist: opentelemetry-api>=1.0.0; extra == 'all'
Requires-Dist: opentelemetry-exporter-otlp-proto-grpc>=1.0.0; extra == 'all'
Requires-Dist: opentelemetry-sdk>=1.0.0; extra == 'all'
Requires-Dist: pytest; extra == 'all'
Requires-Dist: pytest-asyncio; extra == 'all'
Requires-Dist: python-dotenv>=1.2.1; extra == 'all'
Requires-Dist: rich>=10.0.0; extra == 'all'
Requires-Dist: ruff; extra == 'all'
Requires-Dist: types-setuptools; extra == 'all'
Provides-Extra: cli
Requires-Dist: rich>=10.0.0; extra == 'cli'
Provides-Extra: dev
Requires-Dist: mypy; extra == 'dev'
Requires-Dist: pytest; extra == 'dev'
Requires-Dist: pytest-asyncio; extra == 'dev'
Requires-Dist: ruff; extra == 'dev'
Requires-Dist: types-setuptools; extra == 'dev'
Provides-Extra: livekit-example
Requires-Dist: livekit-agents>=1.3.10; extra == 'livekit-example'
Requires-Dist: livekit-plugins-cartesia>=1.3.10; extra == 'livekit-example'
Requires-Dist: livekit-plugins-deepgram>=1.3.10; extra == 'livekit-example'
Requires-Dist: livekit-plugins-openai>=1.3.10; extra == 'livekit-example'
Requires-Dist: livekit-plugins-silero>=1.3.10; extra == 'livekit-example'
Requires-Dist: livekit-plugins-turn-detector>=1.3.10; extra == 'livekit-example'
Requires-Dist: python-dotenv>=1.2.1; extra == 'livekit-example'
Provides-Extra: otel
Requires-Dist: opentelemetry-api>=1.0.0; extra == 'otel'
Requires-Dist: opentelemetry-exporter-otlp-proto-grpc>=1.0.0; extra == 'otel'
Requires-Dist: opentelemetry-sdk>=1.0.0; extra == 'otel'
